slackchannel2pdf/__init__.py
slackchannel2pdf/channel_exporter.py
slackchannel2pdf/cli.py
slackchannel2pdf/fpdf_extension.py
slackchannel2pdf/helpers.py
slackchannel2pdf/locales.py
slackchannel2pdf/message_transformer.py
slackchannel2pdf/settings.py
slackchannel2pdf/slack_service.py
slackchannel2pdf/slackchannel2pdf.ini
slackchannel2pdf/fonts/LICENSE
slackchannel2pdf/fonts/NotoSans-Bold.ttf
slackchannel2pdf/fonts/NotoSans-BoldItalic.ttf
slackchannel2pdf/fonts/NotoSans-Italic.ttf
slackchannel2pdf/fonts/NotoSans-Regular.ttf
slackchannel2pdf/fonts/NotoSansMono-Bold.ttf
slackchannel2pdf/fonts/NotoSansMono-Regular.ttf
slackchannel2pdf/fpdf_mod/__init__.py
slackchannel2pdf/fpdf_mod/fonts.py
slackchannel2pdf/fpdf_mod/fpdf.py
slackchannel2pdf/fpdf_mod/html.py
slackchannel2pdf/fpdf_mod/php.py
slackchannel2pdf/fpdf_mod/py3k.py
slackchannel2pdf/fpdf_mod/template.py
slackchannel2pdf/fpdf_mod/ttfonts.py
slackchannel2pdf-1.5.2.dist-info/entry_points.txt
slackchannel2pdf-1.5.2.dist-info/LICENSE
slackchannel2pdf-1.5.2.dist-info/WHEEL
slackchannel2pdf-1.5.2.dist-info/METADATA
slackchannel2pdf-1.5.2.dist-info/RECORD
