Metadata-Version: 2.1
Name: slackchannel2pdf
Version: 1.5.2
Summary: Command line tool for exporting the text contents of any Slack channel to a PDF file.
Author-email: Erik Kalkoken <kalkoken87@gmail.com>
Requires-Python: >=3.8
Classifier: Environment :: Console
Classifier: Intended Audience :: End Users/Desktop
Classifier: License :: OSI Approved :: MIT License
Classifier: Operating System :: OS Independent
Classifier: Programming Language :: Python
Classifier: Programming Language :: Python :: 3.8
Classifier: Programming Language :: Python :: 3.9
Classifier: Programming Language :: Python :: 3.10
Classifier: Programming Language :: Python :: 3.11
Requires-Dist: Babel>=2.9.1
Requires-Dist: python-dateutil>=2.8.0
Requires-Dist: pytz>=2019.1
Requires-Dist: slack_sdk>=3.15.2
Requires-Dist: tzlocal>=2.0.0
Project-URL: Homepage, https://github.com/ErikKalkoken/slackchannel2pdf
